fdp_eod_checker/__init__.py
fdp_eod_checker/mm_trade.py
fdp_eod_checker/rsec_trade.py
fdp_eod_checker/utils.py
kitetsu/__init__.py
kitetsu/rsec_trade.py
kitetsu/utils.py
fdp_eod_checker-1.0.0.dist-info/METADATA
fdp_eod_checker-1.0.0.dist-info/WHEEL
fdp_eod_checker-1.0.0.dist-info/entry_points.txt
fdp_eod_checker-1.0.0.dist-info/top_level.txt
fdp_eod_checker-1.0.0.dist-info/RECORD
